[
    {
	    "blockquote":"Погано дуже, страх погано! В оцій пустині пропадать. А ще поганше на Украйні Дивитись, плакать – і мовчать.",
	    "author":"Тарас Шевченко",
	    "src":"img/shevchenko.jpg",
	    "alt":"Тарас Шевченко",
      "preference":0,
      "id":0,
	    "show":false
    },
  	{
	    "blockquote":"Учітесь, читайте, І чужому научайтесь, Й свого не цурайтесь.",
	    "author":"Тарас Шевченко",
	    "src":"img/shevchenko.jpg",
	    "alt":"Тарас Шевченко",
      "preference":0,
      "id":1,
	    "show":false
    },
    {
	    "blockquote":"Борітеся – поборете, Вам бог помагає! За вас правда, за вас сила І воля святая! ",
	    "author":"Тарас Шевченко",
	    "src":"img/shevchenko.jpg",
	    "alt":"Тарас Шевченко",
      "preference":0,
      "id":2,
	    "show":false
    },
    {
	    "blockquote":"Страшно впасти у кайдани, Умирать в неволі, А ще гірше – спати, спати, І спати на волі... ",
	    "author":"Тарас Шевченко",
	    "src":"img/shevchenko.jpg",
	    "alt":"Тарас Шевченко",
      "preference":0,
      "id":3,
	    "show":false
    },
    {
      "blockquote":"Людям не те що позакладало вуха – людям позакладало душі",
      "author":"Ліна Костенко",
      "src":"img/kostenko.jpg",
      "alt":"Ліна Костенко",
      "preference":0,
      "id":4,
      "show":false
    },
    {
      "blockquote":"Я тільки не розумію, чому канадський прем’єр-міністр може проїхати до парламенту на ковзанах по замерзлій річці через всю Оттаву, а у нас людей розкидають мало не в кювети, коли їде якесь цабе.",
      "author":"Ліна Костенко",
      "src":"img/kostenko.jpg",
      "alt":"Ліна Костенко",
      "preference":0,
      "id":5,
      "show":false
    },
    {
      "blockquote":"І жах не в тому, що щось зміниться, — жах у тому, що все може залишитися так само.",
      "author":"Ліна Костенко",
      "src":"img/kostenko.jpg",
      "alt":"Ліна Костенко",
      "preference":0,
      "id":6,
      "show":false
    },
    {
      "blockquote":"А секунди летять. Отак можна вмерти й нічого не встигнути. Встигаєш тільки втомитися.",
      "author":"Ліна Костенко",
      "src":"img/kostenko.jpg",
      "alt":"Ліна Костенко",
      "preference":0,
      "id":7,
      "show":false
    },
    {
      "blockquote":"Ми досі ще рятуємо дистрофію тіл, а за прогресуючу дистрофію душ — нам байдуже.",
      "author":"Василь Стус",
      "src":"img/stus.jpg",
      "alt":"Василь Стус",
      "preference":0,
      "id":8,
      "show":false
    },
    {
      "blockquote":"Це щастя: мати таку долю, як у мене…Чуюся добре, бо нікому не зробив зла, бо дбав не тільки про себе. І від того мені світло на душі.",
      "author":"Василь Стус",
      "src":"img/stus.jpg",
      "alt":"Василь Стус",
      "preference":0,
      "id":9,
      "show":false
    },
    {
      "blockquote":"Народ ще тільки осмислює конституційні простори своєї свободи, а уряд уже стріляє.",
      "author":"Василь Стус",
      "src":"img/stus.jpg",
      "alt":"Василь Стус",
      "preference":0,
      "id":10,
      "show":false
    },
    {
      "blockquote":"Кожен кат любить червоне вино, нагріте до 36 градусів.",
      "author":"Василь Стус",
      "src":"img/stus.jpg",
      "alt":"Василь Стус",
      "preference":0,
      "id":11,
      "show":false
    },
    {
      "blockquote":"Немає нічого страшнішого за необмежену владу в руках обмеженої людини.",
      "author":"Василь Симоненко",
      "src":"img/simonenko.jpg",
      "alt":"Василь Симоненко",
      "preference":0,
      "id":12,
      "show":false
    },
    {
      "blockquote":"Вірнішого і сердечнішого побратима, ніж папір, я не знаю.",
      "author":"Василь Симоненко",
      "src":"img/simonenko.jpg",
      "alt":"Василь Симоненко",
      "preference":0,
      "id":13,
      "show":false
    },
    {
      "blockquote":"На світі той намудріший, хто найдужче любить життя.",
      "author":"Василь Симоненко",
      "src":"img/simonenko.jpg",
      "alt":"Василь Симоненко",
      "preference":0,
      "id":14,
      "show":false
    },
    {
      "blockquote":"На цвинтарі розстріляних ілюзій уже немає місця для могил.",
      "author":"Василь Симоненко",
      "src":"img/simonenko.jpg",
      "alt":"Василь Симоненко",
      "preference":0,
      "id":15,
      "show":false
    },
    {
      "blockquote":"Не ридать, а добувать хоч синам, як не собі,кращу долю в боротьбі.",
      "author":"Іван Франко",
      "src":"img/franko.jpg",
      "alt":"Іван Франко",
      "preference":0,
      "id":16,
      "show":false
    },
    {
      "blockquote":"Більш, ніж меч, і огонь, і стріла, і коса,небезпечне оружжя – жіноча краса.",
      "author":"Іван Франко",
      "src":"img/franko.jpg",
      "alt":"Іван Франко",
      "preference":0,
      "id":17,
      "show":false
    },
    {
      "blockquote":"Лиш праця світ таким, як є, створила, лиш в праці і для праці треба жить.",
      "author":"Іван Франко",
      "src":"img/franko.jpg",
      "alt":"Іван Франко",
      "preference":0,
      "id":18,
      "show":false
    },
    {
      "blockquote":"Всяке добро має... й темний бік, а жодне лихо не буває без добра.",
      "author":"Іван Франко",
      "src":"img/franko.jpg",
      "alt":"Іван Франко",
      "preference":0,
      "id":19,
      "show":false
    }

]


